fine_python_isort/__init__.py
fine_python_isort/action.py
fine_python_isort/py.typed
fine_python_isort-0.2.0.dist-info/METADATA
fine_python_isort-0.2.0.dist-info/WHEEL
fine_python_isort-0.2.0.dist-info/top_level.txt
fine_python_isort-0.2.0.dist-info/RECORD
